rtl/alu.sv
typedef enum logic [3:0] {
    ALU_ADD  = 4'b0000,
    ALU_SUB  = 4'b0001,
    ALU_AND  = 4'b0010,
    ALU_OR   = 4'b0011,
    ALU_XOR  = 4'b0100,
    ALU_SLL  = 4'b0101,  // shift left logical
    ALU_SRL  = 4'b0110,  // shift right logical
    ALU_SRA  = 4'b0111,  // shift right arithmetic
    ALU_SLT  = 4'b1000,  // set less than (signed)
    ALU_SLTU = 4'b1001   // set less than (unsigned)
} alu_op_e;

module alu (
    input  logic [31:0] a,
    input  logic [31:0] b,
    input  alu_op_e      op,
    output logic [31:0] result,
    output logic         zero      // 1 when result == 0 — branches (beq) will use this
);

    always_comb begin
        case (op)
            ALU_ADD:  result = a + b;
            ALU_SUB:  result = a - b;
            ALU_AND:  result = a & b;
            ALU_OR:   result = a | b;
            ALU_XOR:  result = a ^ b;
            ALU_SLL:  result = a << b[4:0];
            ALU_SRL:  result = a >> b[4:0];
            ALU_SRA:  result = $signed(a) >>> b[4:0];
            ALU_SLT:  result = ($signed(a) < $signed(b)) ? 32'd1 : 32'd0;
            ALU_SLTU: result = (a < b) ? 32'd1 : 32'd0;
            default:  result = 32'd0;
        endcase
    end

    assign zero = (result == 32'd0);

endmodule

sim/alu_tb.sv
`timescale 1ns/1ps

module alu_tb;

    logic [31:0] a, b;
    alu_op_e      op;
    logic [31:0] result;
    logic         zero;

    int errors = 0;

    alu dut (
        .a      (a),
        .b      (b),
        .op     (op),
        .result (result),
        .zero   (zero)
    );

    task automatic check(
        input logic [31:0] a_in,
        input logic [31:0] b_in,
        input alu_op_e      op_in,
        input logic [31:0] expected,
        input string        name
    );
        a = a_in;
        b = b_in;
        op = op_in;
        #1; // let the always_comb block settle (no clock here, so 1 time unit is plenty)
        if (result !== expected) begin
            $display("FAIL  %-6s  a=%0d b=%0d  got=%0d  expected=%0d",
                      name, a_in, b_in, result, expected);
            errors++;
        end else begin
            $display("pass  %-6s  a=%0d b=%0d  result=%0d", name, a_in, b_in, result);
        end
    endtask

    initial begin
        $dumpfile("alu.vcd");
        $dumpvars(0, alu_tb);

        check(32'd10,  32'd3,   ALU_ADD,  32'd13,          "ADD");
        check(32'd10,  32'd3,   ALU_SUB,  32'd7,           "SUB");
        check(32'hFF,  32'h0F,  ALU_AND,  32'h0F,          "AND");
        check(32'hF0,  32'h0F,  ALU_OR,   32'hFF,          "OR");
        check(32'hFF,  32'h0F,  ALU_XOR,  32'hF0,          "XOR");
        check(32'd1,   32'd4,   ALU_SLL,  32'd16,          "SLL");
        check(32'd16,  32'd2,   ALU_SRL,  32'd4,           "SRL");
        check(-32'd8,  32'd1,   ALU_SRA,  -32'd4,          "SRA");
        check(-32'd5,  32'd3,   ALU_SLT,  32'd1,           "SLT");   // signed: -5 < 3
        check(32'd5,   32'd3,   ALU_SLTU, 32'd0,           "SLTU");  // unsigned: 5 < 3 is false
        check(32'd7,   32'd7,   ALU_SUB,  32'd0,           "ZERO");  // also exercises the zero flag

        // zero flag check on the last op above (7 - 7 = 0)
        if (zero !== 1'b1) begin
            $display("FAIL  zero flag did not assert when result == 0");
            errors++;
        end

        if (errors == 0)
            $display("\nALL TESTS PASSED");
        else
            $display("\n%0d TEST(S) FAILED", errors);

        $finish;
    end

endmodule

alu.vcd
$date
	Thu Sep 10 11:56:03 2026
$end
$version
	Icarus Verilog
$end
$timescale
	1ps
$end
$scope module alu_tb $end
$var wire 1 ! zero $end
$var wire 32 " result [31:0] $end
$var reg 32 # a [31:0] $end
$var reg 32 $ b [31:0] $end
$var reg 4 % op [3:0] $end
$var integer 32 & errors [31:0] $end
$scope module dut $end
$var wire 32 ' a [31:0] $end
$var wire 32 ( b [31:0] $end
$var wire 4 ) op [3:0] $end
$var wire 1 ! zero $end
$var reg 32 * result [31:0] $end
$upscope $end
$scope task check $end
$upscope $end
$upscope $end
$enddefinitions $end
$comment Show the parameter values. $end
$dumpall
$end
#0
$dumpvars
b1101 *
b0 )
b11 (
b1010 '
b0 &
b0 %
b11 $
b1010 #
b1101 "
0!
$end
#1000
b111 "
b111 *
b1 %
b1 )
#2000
b1111 "
b1111 *
b10 %
b10 )
b1111 $
b1111 (
b11111111 #
b11111111 '
#3000
b11111111 "
b11111111 *
b11 %
b11 )
b11110000 #
b11110000 '
#4000
b11110000 "
b11110000 *
b100 %
b100 )
b11111111 #
b11111111 '
#5000
b10000 "
b10000 *
b101 %
b101 )
b100 $
b100 (
b1 #
b1 '
#6000
b100 "
b100 *
b110 %
b110 )
b10 $
b10 (
b10000 #
b10000 '
#7000
b11111111111111111111111111111100 "
b11111111111111111111111111111100 *
b111 %
b111 )
b1 $
b1 (
b11111111111111111111111111111000 #
b11111111111111111111111111111000 '
#8000
b1 "
b1 *
b1000 %
b1000 )
b11 $
b11 (
b11111111111111111111111111111011 #
b11111111111111111111111111111011 '
#9000
1!
b0 "
b0 *
b1001 %
b1001 )
b101 #
b101 '
#10000
b1 %
b1 )
b111 $
b111 (
b111 #
b111 '
